setup.cfg
setup.py
feature_creator_egm/Basic_Feature_Creator.py
feature_creator_egm/FeatureSelector.py
feature_creator_egm/SimpleFeatureSelector.py
feature_creator_egm/Testing_Feature_Selector.py
feature_creator_egm/__init__.py
feature_creator_egm.egg-info/PKG-INFO
feature_creator_egm.egg-info/SOURCES.txt
feature_creator_egm.egg-info/dependency_links.txt
feature_creator_egm.egg-info/not-zip-safe
feature_creator_egm.egg-info/top_level.txt