Metadata-Version: 1.0
Name: feature-creator-egm
Version: 1.0
Summary: feature selector classes
Home-page: UNKNOWN
Author: UNKNOWN
Author-email: UNKNOWN
License: UNKNOWN
Platform: UNKNOWN
